{"BaseModel.5fc22348-d10e-4af5-b470-0d2ad9aa4b4a": {"id": "5fc22348-d10e-4af5-b470-0d2ad9aa4b4a", "created_at": "2023-12-06T17:52:49.293270", "updated_at": "2023-12-06T17:52:49.293270", "__class__": "BaseModel"}, "BaseModel.381a3632-86a4-4d80-a790-fc774f9725bd": {"id": "381a3632-86a4-4d80-a790-fc774f9725bd", "created_at": "2023-12-06T17:52:50.369035", "updated_at": "2023-12-06T17:52:50.369035", "name": "mahmoud", "__class__": "BaseModel"}, "City.1bf1968e-a7ab-4971-9a6b-853820db8fa5": {"id": "1bf1968e-a7ab-4971-9a6b-853820db8fa5", "created_at": "2023-12-07T16:39:03.903105", "updated_at": "2023-12-07T16:39:03.903105", "__class__": "City"}, "BaseModel.8700aa9a-36ca-4a03-a9d9-b1b58d02f60e": {"id": "8700aa9a-36ca-4a03-a9d9-b1b58d02f60e", "created_at": "2023-12-07T16:45:20.870713", "updated_at": "2023-12-07T16:45:20.870813", "name": "My First Model", "my_number": 89, "__class__": "BaseModel"}, "BaseModel.f7ef8caa-e393-4006-b672-563d500865c4": {"id": "f7ef8caa-e393-4006-b672-563d500865c4", "created_at": "2023-12-07T16:45:20.872136", "updated_at": "2023-12-07T16:45:20.872136", "name": "My_First_Model", "my_number": 89, "__class__": "BaseModel"}, "BaseModel.3ea064b5-5ec4-4e95-8fdb-995dede1dbe4": {"id": "3ea064b5-5ec4-4e95-8fdb-995dede1dbe4", "created_at": "2023-12-07T16:45:20.873100", "updated_at": "2023-12-07T16:45:20.873106", "name": "My_First_Model", "my_number": 89, "__class__": "BaseModel"}, "User.af185953-3d24-4451-9af5-6932068ce4d0": {"id": "af185953-3d24-4451-9af5-6932068ce4d0", "created_at": "2023-12-07T16:45:20.880592", "updated_at": "2023-12-07T16:45:20.880606", "first_name": "mahmoud", "last_name": "Bar", "email": "airbnb@mail.com", "password": "root", "{'first_name':": "John", "__class__": "User"}, "User.195d7252-7d28-4a7f-9c2a-36582c35936f": {"id": "195d7252-7d28-4a7f-9c2a-36582c35936f", "created_at": "2023-12-07T16:45:20.881025", "updated_at": "2023-12-07T16:45:20.881038", "first_name": "John", "email": "airbnb2@mail.com", "password": "root", "{\"newName": ":", "__class__": "User"}, "User.c8f4d7c7-6ad8-4a60-81ed-20e07b9d65bf": {"id": "c8f4d7c7-6ad8-4a60-81ed-20e07b9d65bf", "created_at": "2023-12-07T19:57:56.159330", "updated_at": "2023-12-07T19:57:56.159330", "name": "mahmoudpop", "age": "22", "{attr_name}": "{attr_value}", "__class__": "User"}, "User.be25479e-070f-4151-93d8-087077cd6c01": {"id": "be25479e-070f-4151-93d8-087077cd6c01", "created_at": "2023-12-07T20:07:50.210370", "updated_at": "2023-12-07T20:07:50.210370", "name": "mahmoud", "age": "20", "__class__": "User"}}